LICENSE
MANIFEST.in
README.md
RELEASE-VERSION
requirements.txt
rpm-install-script.sh
settings.py
setup.py
version.py
examples/__init__.py
examples/analytics.py
examples/regex_search.py
examples/simple.py
examples/util.py
examples/indexed_doc_iterator/ingest.py
examples/indexed_doc_iterator/search.py
examples/intersecting_iterator/ingest.py
examples/intersecting_iterator/search.py
pyaccumulo/__init__.py
pyaccumulo.egg-info/PKG-INFO
pyaccumulo.egg-info/SOURCES.txt
pyaccumulo.egg-info/dependency_links.txt
pyaccumulo.egg-info/requires.txt
pyaccumulo.egg-info/top_level.txt
pyaccumulo/iterators/__init__.py
pyaccumulo/proxy/AccumuloProxy.py
pyaccumulo/proxy/__init__.py
pyaccumulo/proxy/constants.py
pyaccumulo/proxy/ttypes.py
tests/__init__.py
tests/test_core.py
tests/test_iterator.py