Metadata-Version: 1.1
Name: pyaccumulo
Version: 1.5.0.9
Summary: Python client library for Apache Accumulo
Home-page: https://github.com/accumulo/pyaccumulo
Author: Jason Trost
Author-email: jason.trost@gmail.com
License: License :: OSI Approved :: Apache Software License
Keywords: accumulo client db distributed thrift
Platform: UNKNOWN
Classifier: Development Status :: 3 - Alpha
Classifier: Intended Audience :: Developers
Classifier: License :: OSI Approved :: Apache Software License
Classifier: Natural Language :: English
Classifier: Operating System :: OS Independent
Classifier: Programming Language :: Python
Classifier: Programming Language :: Python :: 2
Classifier: Programming Language :: Python :: 2.6
Classifier: Programming Language :: Python :: 2.7
Classifier: Programming Language :: Python :: 2 :: Only
Classifier: Topic :: Software Development :: Libraries :: Python Modules
